build/lib/dining_philosophers/__init__.py
build/lib/dining_philosophers/main.py
build/lib/dining_philosophers/version.py
dining_philosophers/__init__.py
dining_philosophers/main.py
dining_philosophers/version.py
dining_philosophers/src/dining_philosophers.py
dining_philosophers/src/dining_simulation.py
dining_philosophers/src/philosopher.py
dining_philosophers/src/stick.py
tests/test_sample.py
dining_philosophers-0.2.0.dist-info/LICENSE
dining_philosophers-0.2.0.dist-info/METADATA
dining_philosophers-0.2.0.dist-info/WHEEL
dining_philosophers-0.2.0.dist-info/entry_points.txt
dining_philosophers-0.2.0.dist-info/top_level.txt
dining_philosophers-0.2.0.dist-info/RECORD
